pyanglianwater/__init__.py
pyanglianwater/_version.py
pyanglianwater/api.py
pyanglianwater/auth.py
pyanglianwater/const.py
pyanglianwater/enum.py
pyanglianwater/exceptions.py
pyanglianwater/meter.py
pyanglianwater/py.typed
pyanglianwater/utils.py
pyanglianwater-2025.6.0.dist-info/licenses/LICENSE
pyanglianwater-2025.6.0.dist-info/METADATA
pyanglianwater-2025.6.0.dist-info/WHEEL
pyanglianwater-2025.6.0.dist-info/top_level.txt
pyanglianwater-2025.6.0.dist-info/RECORD
