Metadata-Version: 2.4
Name: pyanglianwater
Version: 2025.6.0
Summary: A package to interact with Anglian Water
Home-page: http://github.com/pantherale0/pyanglianwater
Author: pantherale0
License: MIT
Classifier: Programming Language :: Python :: 3
Classifier: License :: OSI Approved :: MIT License
Classifier: Operating System :: OS Independent
Requires-Python: >=3.10, <4
License-File: LICENSE
Requires-Dist: pyjwt<3,>=2.6
Requires-Dist: fiscalyear>=0.4.0
Provides-Extra: dev
Requires-Dist: bandit<1.9,>=1.7; extra == "dev"
Requires-Dist: black<26,>=24; extra == "dev"
Requires-Dist: build<1.3,>=1.1; extra == "dev"
Requires-Dist: flake8==7.*; extra == "dev"
Requires-Dist: isort<7,>=5; extra == "dev"
Requires-Dist: mypy<1.17,>=1.9; extra == "dev"
Requires-Dist: pytest==8.*; extra == "dev"
Requires-Dist: pytest-cov<7,>=4; extra == "dev"
Requires-Dist: twine<7,>=4; extra == "dev"
Dynamic: author
Dynamic: classifier
Dynamic: description
Dynamic: description-content-type
Dynamic: home-page
Dynamic: license
Dynamic: license-file
Dynamic: provides-extra
Dynamic: requires-dist
Dynamic: requires-python
Dynamic: summary
